openbci_interface/VERSION
openbci_interface/__init__.py
openbci_interface/__main__.py
openbci_interface/_version.py
openbci_interface/channel_config.py
openbci_interface/core.py
openbci_interface/cyton.py
openbci_interface/exception.py
openbci_interface/util.py
openbci_interface/command/__init__.py
openbci_interface/command/list_devices.py
openbci_interface/command/stream.py
openbci_interface-0.8.0.dist-info/METADATA
openbci_interface-0.8.0.dist-info/RECORD
openbci_interface-0.8.0.dist-info/WHEEL
openbci_interface-0.8.0.dist-info/entry_points.txt
openbci_interface-0.8.0.dist-info/top_level.txt
