Metadata-Version: 2.1
Name: openbci-interface
Version: 0.8.0
Summary: Simple interface to OpenBCI hardware
Home-page: https://github.com/hellomoto-ai/openbci-interface
Author: moto
Author-email: moto@hellomoto.ai
License: UNKNOWN
Platform: UNKNOWN
Classifier: Programming Language :: Python :: 3
Classifier: License :: OSI Approved :: MIT License
Classifier: Operating System :: OS Independent
Provides-Extra: dev
Requires-Dist: pyserial (<3.5)
Provides-Extra: dev
Requires-Dist: pylint; extra == 'dev'
Requires-Dist: flake8; extra == 'dev'
Requires-Dist: flake8-print; extra == 'dev'
Requires-Dist: pytest; extra == 'dev'
Requires-Dist: pytest-cov; extra == 'dev'
Requires-Dist: pytest-mock; extra == 'dev'
